tablestore_openmemory_mcp/__init__.py
tablestore_openmemory_mcp/main.py
tablestore_openmemory_mcp/mcp_server.py
tablestore_openmemory_mcp/settings.py
tablestore_openmemory_mcp/mem0_wheel/mem0ai-0.1.114-py3-none-any.whl
tablestore_openmemory_mcp-1.2.2.dist-info/METADATA
tablestore_openmemory_mcp-1.2.2.dist-info/WHEEL
tablestore_openmemory_mcp-1.2.2.dist-info/entry_points.txt
tablestore_openmemory_mcp-1.2.2.dist-info/licenses/LICENSE
tablestore_openmemory_mcp-1.2.2.dist-info/RECORD
