Metadata-Version: 2.4
Name: tablestore-openmemory-mcp
Version: 1.2.2
Summary: MCP server for retrieving context from a tablestore vector database
License-Expression: Apache-2.0
License-File: LICENSE
Requires-Python: <4.0,>=3.10
Requires-Dist: fastapi==0.116.0
Requires-Dist: fastmcp>=2.3.4
Requires-Dist: mcp[cli]>=1.10.1
Requires-Dist: mem0ai
Requires-Dist: pydantic-settings>=2.10.1
Requires-Dist: tablestore-for-agent-memory>=1.1.2
Requires-Dist: tablestore>=6.3.8
